{
  "CodeKitInfo" : "This is a CodeKit project configuration file. It is designed to sync project settings across multiple machines. Modifying the contents of this file can be a poor life decision if you don't know what you're doing. This file is not useful unless accompanied by the project that created it in CodeKit. For more information, see: http:\/\/incident57.com\/codekit",
  "creatorBuild" : "8283",
  "files" : {
    "\/images\/facebook_circle@2x.png" : {
      "ignoreWasSetByUser" : 0,
      "ignore" : 0,
      "hidden" : 0,
      "outputPathIsSetByUser" : 0,
      "inputAbbreviatedPath" : "\/images\/facebook_circle@2x.png",
      "processed" : 0,
      "outputAbbreviatedPath" : "\/images\/facebook_circle@2x.png",
      "initialSize" : 1884,
      "fileType" : 8192
    },
    "\/sass\/_1030up.scss" : {
      "ignoreWasSetByUser" : 0,
      "ignore" : 1,
      "hidden" : 0,
      "outputPathIsSetByUser" : 0,
      "inputAbbreviatedPath" : "\/sass\/_1030up.scss",
      "outputStyle" : 3,
      "shouldRunBless" : 0,
      "outputAbbreviatedPath" : "\/css\/_1030up.css",
      "fileType" : 4,
      "debugStyle" : 0
    },
    "\/scss\/_2x.scss" : {
      "ignoreWasSetByUser" : 0,
      "ignore" : 1,
      "hidden" : 0,
      "outputPathIsSetByUser" : 0,
      "inputAbbreviatedPath" : "\/scss\/_2x.scss",
      "outputStyle" : 3,
      "shouldRunBless" : 0,
      "outputAbbreviatedPath" : "\/css\/_2x.css",
      "fileType" : 4,
      "debugStyle" : 0
    },
    "\/css\/demo.html" : {
      "ignoreWasSetByUser" : 0,
      "ignore" : 0,
      "hidden" : 0,
      "outputPathIsSetByUser" : 0,
      "inputAbbreviatedPath" : "\/css\/demo.html",
      "outputAbbreviatedPath" : "No Output Path",
      "fileType" : 2048
    },
    "\/images\/rss_circle.png" : {
      "ignoreWasSetByUser" : 0,
      "ignore" : 0,
      "hidden" : 0,
      "outputPathIsSetByUser" : 0,
      "inputAbbreviatedPath" : "\/images\/rss_circle.png",
      "processed" : 0,
      "outputAbbreviatedPath" : "\/images\/rss_circle.png",
      "initialSize" : 1193,
      "fileType" : 8192
    },
    "\/less\/_1240up.less" : {
      "ignoreWasSetByUser" : 0,
      "ignore" : 1,
      "hidden" : 0,
      "outputPathIsSetByUser" : 0,
      "inputAbbreviatedPath" : "\/less\/_1240up.less",
      "outputStyle" : 0,
      "shouldRunBless" : 0,
      "outputAbbreviatedPath" : "\/css\/_1240up.css",
      "strictImports" : 0,
      "fileType" : 1,
      "debugStyle" : 0
    },
    "\/less\/_1030up.less" : {
      "ignoreWasSetByUser" : 0,
      "ignore" : 1,
      "hidden" : 0,
      "outputPathIsSetByUser" : 0,
      "inputAbbreviatedPath" : "\/less\/_1030up.less",
      "outputStyle" : 0,
      "shouldRunBless" : 0,
      "outputAbbreviatedPath" : "\/css\/_1030up.css",
      "strictImports" : 0,
      "fileType" : 1,
      "debugStyle" : 0
    },
    "\/less\/_print.less" : {
      "ignoreWasSetByUser" : 0,
      "ignore" : 1,
      "hidden" : 0,
      "outputPathIsSetByUser" : 0,
      "inputAbbreviatedPath" : "\/less\/_print.less",
      "outputStyle" : 0,
      "shouldRunBless" : 0,
      "outputAbbreviatedPath" : "\/css\/_print.css",
      "strictImports" : 0,
      "fileType" : 1,
      "debugStyle" : 0
    },
    "\/sass\/ie.scss" : {
      "ignoreWasSetByUser" : 0,
      "ignore" : 0,
      "hidden" : 0,
      "outputPathIsSetByUser" : 0,
      "inputAbbreviatedPath" : "\/sass\/ie.scss",
      "outputStyle" : 3,
      "shouldRunBless" : 0,
      "outputAbbreviatedPath" : "\/css\/ie.css",
      "fileType" : 4,
      "debugStyle" : 0
    },
    "\/images\/youtube_circle@2x.png" : {
      "ignoreWasSetByUser" : 0,
      "ignore" : 0,
      "hidden" : 0,
      "outputPathIsSetByUser" : 0,
      "inputAbbreviatedPath" : "\/images\/youtube_circle@2x.png",
      "processed" : 0,
      "outputAbbreviatedPath" : "\/images\/youtube_circle@2x.png",
      "initialSize" : 2694,
      "fileType" : 8192
    },
    "\/scss\/_grid.scss" : {
      "ignoreWasSetByUser" : 0,
      "ignore" : 1,
      "hidden" : 0,
      "outputPathIsSetByUser" : 0,
      "inputAbbreviatedPath" : "\/scss\/_grid.scss",
      "outputStyle" : 3,
      "shouldRunBless" : 0,
      "outputAbbreviatedPath" : "\/css\/_grid.css",
      "fileType" : 4,
      "debugStyle" : 0
    },
    "\/scss\/not_used\/buttons_full.scss" : {
      "ignoreWasSetByUser" : 0,
      "ignore" : 0,
      "hidden" : 0,
      "outputPathIsSetByUser" : 0,
      "inputAbbreviatedPath" : "\/scss\/not_used\/buttons_full.scss",
      "outputStyle" : 3,
      "shouldRunBless" : 0,
      "outputAbbreviatedPath" : "\/scss\/css\/buttons_full.css",
      "fileType" : 4,
      "debugStyle" : 0
    },
    "\/css\/_mixins.css" : {
      "ignoreWasSetByUser" : 0,
      "ignore" : 1,
      "hidden" : 0,
      "outputPathIsSetByUser" : 0,
      "inputAbbreviatedPath" : "\/css\/_mixins.css",
      "outputAbbreviatedPath" : "No Output Path",
      "fileType" : 16
    },
    "\/images\/give3.png" : {
      "ignoreWasSetByUser" : 0,
      "ignore" : 0,
      "hidden" : 0,
      "outputPathIsSetByUser" : 0,
      "inputAbbreviatedPath" : "\/images\/give3.png",
      "processed" : 0,
      "outputAbbreviatedPath" : "\/images\/give3.png",
      "initialSize" : 4570,
      "fileType" : 8192
    },
    "\/sass\/_base.scss" : {
      "ignoreWasSetByUser" : 0,
      "ignore" : 1,
      "hidden" : 0,
      "outputPathIsSetByUser" : 0,
      "inputAbbreviatedPath" : "\/sass\/_base.scss",
      "outputStyle" : 3,
      "shouldRunBless" : 0,
      "outputAbbreviatedPath" : "\/css\/_base.css",
      "fileType" : 4,
      "debugStyle" : 0
    },
    "\/custom-post-type.php" : {
      "ignoreWasSetByUser" : 0,
      "ignore" : 0,
      "hidden" : 0,
      "outputPathIsSetByUser" : 0,
      "inputAbbreviatedPath" : "\/custom-post-type.php",
      "outputAbbreviatedPath" : "No Output Path",
      "fileType" : 2048
    },
    "\/images\/flickr_circle.png" : {
      "ignoreWasSetByUser" : 0,
      "ignore" : 0,
      "hidden" : 0,
      "outputPathIsSetByUser" : 0,
      "inputAbbreviatedPath" : "\/images\/flickr_circle.png",
      "processed" : 0,
      "outputAbbreviatedPath" : "\/images\/flickr_circle.png",
      "initialSize" : 898,
      "fileType" : 8192
    },
    "\/js\/scripts-ck.js" : {
      "ignoreWasSetByUser" : 0,
      "ignore" : 1,
      "hidden" : 0,
      "outputPathIsSetByUser" : 0,
      "inputAbbreviatedPath" : "\/js\/scripts-ck.js",
      "outputStyle" : 1,
      "syntaxCheckerStyle" : 1,
      "outputAbbreviatedPath" : "\/js\/scripts-ck-ck.js",
      "fileType" : 64
    },
    "\/images\/close-icon-large.png" : {
      "ignoreWasSetByUser" : 0,
      "ignore" : 0,
      "hidden" : 0,
      "outputPathIsSetByUser" : 0,
      "inputAbbreviatedPath" : "\/images\/close-icon-large.png",
      "processed" : 0,
      "outputAbbreviatedPath" : "\/images\/close-icon-large.png",
      "initialSize" : 1852,
      "fileType" : 8192
    },
    "\/css\/screen.css" : {
      "ignoreWasSetByUser" : 0,
      "ignore" : 0,
      "hidden" : 0,
      "outputPathIsSetByUser" : 0,
      "inputAbbreviatedPath" : "\/css\/screen.css",
      "outputAbbreviatedPath" : "No Output Path",
      "fileType" : 16
    },
    "\/images\/volunteer2.png" : {
      "ignoreWasSetByUser" : 0,
      "ignore" : 0,
      "hidden" : 0,
      "outputPathIsSetByUser" : 0,
      "inputAbbreviatedPath" : "\/images\/volunteer2.png",
      "processed" : 0,
      "outputAbbreviatedPath" : "\/images\/volunteer2.png",
      "initialSize" : 3318,
      "fileType" : 8192
    },
    "\/sass\/_481up.scss" : {
      "ignoreWasSetByUser" : 0,
      "ignore" : 1,
      "hidden" : 0,
      "outputPathIsSetByUser" : 0,
      "inputAbbreviatedPath" : "\/sass\/_481up.scss",
      "outputStyle" : 3,
      "shouldRunBless" : 0,
      "outputAbbreviatedPath" : "\/css\/_481up.css",
      "fileType" : 4,
      "debugStyle" : 0
    },
    "\/css\/not_used\/style.css" : {
      "ignoreWasSetByUser" : 0,
      "ignore" : 0,
      "hidden" : 0,
      "outputPathIsSetByUser" : 0,
      "inputAbbreviatedPath" : "\/css\/not_used\/style.css",
      "outputAbbreviatedPath" : "No Output Path",
      "fileType" : 16
    },
    "\/fonts\/style.css" : {
      "ignoreWasSetByUser" : 0,
      "ignore" : 0,
      "hidden" : 0,
      "outputPathIsSetByUser" : 0,
      "inputAbbreviatedPath" : "\/fonts\/style.css",
      "outputAbbreviatedPath" : "No Output Path",
      "fileType" : 16
    },
    "\/less\/_768up.less" : {
      "ignoreWasSetByUser" : 0,
      "ignore" : 1,
      "hidden" : 0,
      "outputPathIsSetByUser" : 0,
      "inputAbbreviatedPath" : "\/less\/_768up.less",
      "outputStyle" : 0,
      "shouldRunBless" : 0,
      "outputAbbreviatedPath" : "\/css\/_768up.css",
      "strictImports" : 0,
      "fileType" : 1,
      "debugStyle" : 0
    },
    "\/scss\/_1240up.scss" : {
      "ignoreWasSetByUser" : 0,
      "ignore" : 1,
      "hidden" : 0,
      "outputPathIsSetByUser" : 0,
      "inputAbbreviatedPath" : "\/scss\/_1240up.scss",
      "outputStyle" : 3,
      "shouldRunBless" : 0,
      "outputAbbreviatedPath" : "\/css\/_1240up.css",
      "fileType" : 4,
      "debugStyle" : 0
    },
    "\/images\/give2@2x.png" : {
      "ignoreWasSetByUser" : 0,
      "ignore" : 0,
      "hidden" : 0,
      "outputPathIsSetByUser" : 0,
      "inputAbbreviatedPath" : "\/images\/give2@2x.png",
      "processed" : 0,
      "outputAbbreviatedPath" : "\/images\/give2@2x.png",
      "initialSize" : 3316,
      "fileType" : 8192
    },
    "\/fonts\/glyphs.html" : {
      "ignoreWasSetByUser" : 0,
      "ignore" : 0,
      "hidden" : 0,
      "outputPathIsSetByUser" : 0,
      "inputAbbreviatedPath" : "\/fonts\/glyphs.html",
      "outputAbbreviatedPath" : "No Output Path",
      "fileType" : 2048
    },
    "\/images\/give2.png" : {
      "ignoreWasSetByUser" : 0,
      "ignore" : 0,
      "hidden" : 0,
      "outputPathIsSetByUser" : 0,
      "inputAbbreviatedPath" : "\/images\/give2.png",
      "processed" : 0,
      "outputAbbreviatedPath" : "\/images\/give2.png",
      "initialSize" : 1642,
      "fileType" : 8192
    },
    "\/less\/_grid.less" : {
      "ignoreWasSetByUser" : 0,
      "ignore" : 1,
      "hidden" : 0,
      "outputPathIsSetByUser" : 0,
      "inputAbbreviatedPath" : "\/less\/_grid.less",
      "outputStyle" : 0,
      "shouldRunBless" : 0,
      "outputAbbreviatedPath" : "\/css\/_grid.css",
      "strictImports" : 0,
      "fileType" : 1,
      "debugStyle" : 0
    },
    "\/sass\/style.scss" : {
      "ignoreWasSetByUser" : 0,
      "ignore" : 0,
      "hidden" : 0,
      "outputPathIsSetByUser" : 0,
      "inputAbbreviatedPath" : "\/sass\/style.scss",
      "outputStyle" : 3,
      "shouldRunBless" : 0,
      "outputAbbreviatedPath" : "\/css\/style.css",
      "fileType" : 4,
      "debugStyle" : 0
    },
    "\/images\/volunteer.png" : {
      "ignoreWasSetByUser" : 0,
      "ignore" : 0,
      "hidden" : 0,
      "outputPathIsSetByUser" : 0,
      "inputAbbreviatedPath" : "\/images\/volunteer.png",
      "processed" : 0,
      "outputAbbreviatedPath" : "\/images\/volunteer.png",
      "initialSize" : 727,
      "fileType" : 8192
    },
    "\/scss\/not_used\/_common_new.scss" : {
      "ignoreWasSetByUser" : 0,
      "ignore" : 1,
      "hidden" : 0,
      "outputPathIsSetByUser" : 0,
      "inputAbbreviatedPath" : "\/scss\/not_used\/_common_new.scss",
      "outputStyle" : 3,
      "shouldRunBless" : 0,
      "outputAbbreviatedPath" : "\/scss\/css\/_common_new.css",
      "fileType" : 4,
      "debugStyle" : 0
    },
    "\/images\/volunteer2@2x.png" : {
      "ignoreWasSetByUser" : 0,
      "ignore" : 0,
      "hidden" : 0,
      "outputPathIsSetByUser" : 0,
      "inputAbbreviatedPath" : "\/images\/volunteer2@2x.png",
      "processed" : 0,
      "outputAbbreviatedPath" : "\/images\/volunteer2@2x.png",
      "initialSize" : 5421,
      "fileType" : 8192
    },
    "\/less\/_2x.less" : {
      "ignoreWasSetByUser" : 0,
      "ignore" : 1,
      "hidden" : 0,
      "outputPathIsSetByUser" : 0,
      "inputAbbreviatedPath" : "\/less\/_2x.less",
      "outputStyle" : 0,
      "shouldRunBless" : 0,
      "outputAbbreviatedPath" : "\/css\/_2x.css",
      "strictImports" : 0,
      "fileType" : 1,
      "debugStyle" : 0
    },
    "\/images\/give3@2x.png" : {
      "ignoreWasSetByUser" : 0,
      "ignore" : 0,
      "hidden" : 0,
      "outputPathIsSetByUser" : 0,
      "inputAbbreviatedPath" : "\/images\/give3@2x.png",
      "processed" : 0,
      "outputAbbreviatedPath" : "\/images\/give3@2x.png",
      "initialSize" : 8984,
      "fileType" : 8192
    },
    "\/scss\/style.scss" : {
      "ignoreWasSetByUser" : 0,
      "ignore" : 0,
      "hidden" : 0,
      "outputPathIsSetByUser" : 0,
      "inputAbbreviatedPath" : "\/scss\/style.scss",
      "outputStyle" : 3,
      "shouldRunBless" : 0,
      "outputAbbreviatedPath" : "\/css\/style.css",
      "fileType" : 4,
      "debugStyle" : 0
    },
    "\/stylesheets\/style.css" : {
      "ignoreWasSetByUser" : 0,
      "ignore" : 0,
      "hidden" : 0,
      "outputPathIsSetByUser" : 0,
      "inputAbbreviatedPath" : "\/stylesheets\/style.css",
      "outputAbbreviatedPath" : "No Output Path",
      "fileType" : 16
    },
    "\/scss\/_base.scss" : {
      "ignoreWasSetByUser" : 0,
      "ignore" : 1,
      "hidden" : 0,
      "outputPathIsSetByUser" : 0,
      "inputAbbreviatedPath" : "\/scss\/_base.scss",
      "outputStyle" : 3,
      "shouldRunBless" : 0,
      "outputAbbreviatedPath" : "\/css\/_base.css",
      "fileType" : 4,
      "debugStyle" : 0
    },
    "\/sass\/css\/occ_buttons.css" : {
      "ignoreWasSetByUser" : 0,
      "ignore" : 1,
      "hidden" : 0,
      "outputPathIsSetByUser" : 0,
      "inputAbbreviatedPath" : "\/sass\/css\/occ_buttons.css",
      "outputAbbreviatedPath" : "No Output Path",
      "fileType" : 16
    },
    "\/sass\/_common.scss" : {
      "ignoreWasSetByUser" : 0,
      "ignore" : 1,
      "hidden" : 0,
      "outputPathIsSetByUser" : 0,
      "inputAbbreviatedPath" : "\/sass\/_common.scss",
      "outputStyle" : 3,
      "shouldRunBless" : 0,
      "outputAbbreviatedPath" : "\/css\/_common.css",
      "fileType" : 4,
      "debugStyle" : 0
    },
    "\/sass\/login.scss" : {
      "ignoreWasSetByUser" : 0,
      "ignore" : 0,
      "hidden" : 0,
      "outputPathIsSetByUser" : 0,
      "inputAbbreviatedPath" : "\/sass\/login.scss",
      "outputStyle" : 3,
      "shouldRunBless" : 0,
      "outputAbbreviatedPath" : "\/css\/login.css",
      "fileType" : 4,
      "debugStyle" : 0
    },
    "\/images\/youtube_circle.png" : {
      "ignoreWasSetByUser" : 0,
      "ignore" : 0,
      "hidden" : 0,
      "outputPathIsSetByUser" : 0,
      "inputAbbreviatedPath" : "\/images\/youtube_circle.png",
      "processed" : 0,
      "outputAbbreviatedPath" : "\/images\/youtube_circle.png",
      "initialSize" : 1363,
      "fileType" : 8192
    },
    "\/scss\/login.scss" : {
      "ignoreWasSetByUser" : 0,
      "ignore" : 0,
      "hidden" : 0,
      "outputPathIsSetByUser" : 0,
      "inputAbbreviatedPath" : "\/scss\/login.scss",
      "outputStyle" : 3,
      "shouldRunBless" : 0,
      "outputAbbreviatedPath" : "\/css\/login.css",
      "fileType" : 4,
      "debugStyle" : 0
    },
    "\/scss\/css\/occ_buttons.css" : {
      "ignoreWasSetByUser" : 0,
      "ignore" : 1,
      "hidden" : 0,
      "outputPathIsSetByUser" : 0,
      "inputAbbreviatedPath" : "\/scss\/css\/occ_buttons.css",
      "outputAbbreviatedPath" : "No Output Path",
      "fileType" : 16
    },
    "\/js\/uwmctweets.js" : {
      "ignoreWasSetByUser" : 0,
      "ignore" : 0,
      "hidden" : 0,
      "outputPathIsSetByUser" : 0,
      "inputAbbreviatedPath" : "\/js\/uwmctweets.js",
      "outputStyle" : 1,
      "syntaxCheckerStyle" : 1,
      "outputAbbreviatedPath" : "\/js\/uwmctweets-ck.js",
      "fileType" : 64
    },
    "\/css\/login.css" : {
      "ignoreWasSetByUser" : 0,
      "ignore" : 1,
      "hidden" : 0,
      "outputPathIsSetByUser" : 0,
      "inputAbbreviatedPath" : "\/css\/login.css",
      "outputAbbreviatedPath" : "No Output Path",
      "fileType" : 16
    },
    "\/scss\/_481up.scss" : {
      "ignoreWasSetByUser" : 0,
      "ignore" : 1,
      "hidden" : 0,
      "outputPathIsSetByUser" : 0,
      "inputAbbreviatedPath" : "\/scss\/_481up.scss",
      "outputStyle" : 3,
      "shouldRunBless" : 0,
      "outputAbbreviatedPath" : "\/css\/_481up.css",
      "fileType" : 4,
      "debugStyle" : 0
    },
    "\/scss\/not_used\/occ_buttons.scss" : {
      "ignoreWasSetByUser" : 0,
      "ignore" : 0,
      "hidden" : 0,
      "outputPathIsSetByUser" : 0,
      "inputAbbreviatedPath" : "\/scss\/not_used\/occ_buttons.scss",
      "outputStyle" : 3,
      "shouldRunBless" : 0,
      "outputAbbreviatedPath" : "\/scss\/css\/occ_buttons.css",
      "fileType" : 4,
      "debugStyle" : 0
    },
    "\/scss\/ie.scss" : {
      "ignoreWasSetByUser" : 0,
      "ignore" : 0,
      "hidden" : 0,
      "outputPathIsSetByUser" : 0,
      "inputAbbreviatedPath" : "\/scss\/ie.scss",
      "outputStyle" : 3,
      "shouldRunBless" : 0,
      "outputAbbreviatedPath" : "\/css\/ie.css",
      "fileType" : 4,
      "debugStyle" : 0
    },
    "\/sass\/_mixins.scss" : {
      "ignoreWasSetByUser" : 0,
      "ignore" : 1,
      "hidden" : 0,
      "outputPathIsSetByUser" : 0,
      "inputAbbreviatedPath" : "\/sass\/_mixins.scss",
      "outputStyle" : 3,
      "shouldRunBless" : 0,
      "outputAbbreviatedPath" : "\/css\/_mixins.css",
      "fileType" : 4,
      "debugStyle" : 0
    },
    "\/js\/scripts.js" : {
      "ignoreWasSetByUser" : 0,
      "ignore" : 0,
      "hidden" : 0,
      "outputPathIsSetByUser" : 0,
      "inputAbbreviatedPath" : "\/js\/scripts.js",
      "outputStyle" : 1,
      "syntaxCheckerStyle" : 1,
      "outputAbbreviatedPath" : "\/js\/scripts-ck.js",
      "fileType" : 64
    },
    "\/less\/_normalize.less" : {
      "ignoreWasSetByUser" : 0,
      "ignore" : 1,
      "hidden" : 0,
      "outputPathIsSetByUser" : 0,
      "inputAbbreviatedPath" : "\/less\/_normalize.less",
      "outputStyle" : 0,
      "shouldRunBless" : 0,
      "outputAbbreviatedPath" : "\/css\/_normalize.css",
      "strictImports" : 0,
      "fileType" : 1,
      "debugStyle" : 0
    },
    "\/demo.php" : {
      "ignoreWasSetByUser" : 0,
      "ignore" : 0,
      "hidden" : 0,
      "outputPathIsSetByUser" : 0,
      "inputAbbreviatedPath" : "\/demo.php",
      "outputAbbreviatedPath" : "No Output Path",
      "fileType" : 2048
    },
    "\/images\/logo-mobile.png" : {
      "ignoreWasSetByUser" : 0,
      "ignore" : 0,
      "hidden" : 0,
      "outputPathIsSetByUser" : 0,
      "inputAbbreviatedPath" : "\/images\/logo-mobile.png",
      "processed" : 0,
      "outputAbbreviatedPath" : "\/images\/logo-mobile.png",
      "initialSize" : 14257,
      "fileType" : 8192
    },
    "\/scss\/not_used\/_mixins_old.scss" : {
      "ignoreWasSetByUser" : 0,
      "ignore" : 1,
      "hidden" : 0,
      "outputPathIsSetByUser" : 0,
      "inputAbbreviatedPath" : "\/scss\/not_used\/_mixins_old.scss",
      "outputStyle" : 3,
      "shouldRunBless" : 0,
      "outputAbbreviatedPath" : "\/scss\/css\/_mixins_old.css",
      "fileType" : 4,
      "debugStyle" : 0
    },
    "\/css\/_buttons.css" : {
      "ignoreWasSetByUser" : 0,
      "ignore" : 1,
      "hidden" : 0,
      "outputPathIsSetByUser" : 0,
      "inputAbbreviatedPath" : "\/css\/_buttons.css",
      "outputAbbreviatedPath" : "No Output Path",
      "fileType" : 16
    },
    "\/images\/glyphicons-halflings.png" : {
      "ignoreWasSetByUser" : 0,
      "ignore" : 0,
      "hidden" : 0,
      "outputPathIsSetByUser" : 0,
      "inputAbbreviatedPath" : "\/images\/glyphicons-halflings.png",
      "processed" : 0,
      "outputAbbreviatedPath" : "\/images\/glyphicons-halflings.png",
      "initialSize" : 12799,
      "fileType" : 8192
    },
    "\/css\/_common.css" : {
      "ignoreWasSetByUser" : 0,
      "ignore" : 1,
      "hidden" : 0,
      "outputPathIsSetByUser" : 0,
      "inputAbbreviatedPath" : "\/css\/_common.css",
      "outputAbbreviatedPath" : "No Output Path",
      "fileType" : 16
    },
    "\/less\/_mixins.less" : {
      "ignoreWasSetByUser" : 0,
      "ignore" : 1,
      "hidden" : 0,
      "outputPathIsSetByUser" : 0,
      "inputAbbreviatedPath" : "\/less\/_mixins.less",
      "outputStyle" : 0,
      "shouldRunBless" : 0,
      "outputAbbreviatedPath" : "\/css\/_mixins.css",
      "strictImports" : 0,
      "fileType" : 1,
      "debugStyle" : 0
    },
    "\/scss\/_1030up.scss" : {
      "ignoreWasSetByUser" : 0,
      "ignore" : 1,
      "hidden" : 0,
      "outputPathIsSetByUser" : 0,
      "inputAbbreviatedPath" : "\/scss\/_1030up.scss",
      "outputStyle" : 3,
      "shouldRunBless" : 0,
      "outputAbbreviatedPath" : "\/css\/_1030up.css",
      "fileType" : 4,
      "debugStyle" : 0
    },
    "\/less\/style.less" : {
      "ignoreWasSetByUser" : 0,
      "ignore" : 0,
      "hidden" : 0,
      "outputPathIsSetByUser" : 0,
      "inputAbbreviatedPath" : "\/less\/style.less",
      "outputStyle" : 0,
      "shouldRunBless" : 0,
      "outputAbbreviatedPath" : "\/css\/style.css",
      "strictImports" : 0,
      "fileType" : 1,
      "debugStyle" : 0
    },
    "\/sass\/_normalize.scss" : {
      "ignoreWasSetByUser" : 0,
      "ignore" : 1,
      "hidden" : 0,
      "outputPathIsSetByUser" : 0,
      "inputAbbreviatedPath" : "\/sass\/_normalize.scss",
      "outputStyle" : 3,
      "shouldRunBless" : 0,
      "outputAbbreviatedPath" : "\/css\/_normalize.css",
      "fileType" : 4,
      "debugStyle" : 0
    },
    "\/less\/_base.less" : {
      "ignoreWasSetByUser" : 0,
      "ignore" : 1,
      "hidden" : 0,
      "outputPathIsSetByUser" : 0,
      "inputAbbreviatedPath" : "\/less\/_base.less",
      "outputStyle" : 0,
      "shouldRunBless" : 0,
      "outputAbbreviatedPath" : "\/css\/_base.css",
      "strictImports" : 0,
      "fileType" : 1,
      "debugStyle" : 0
    },
    "\/sass\/_2x.scss" : {
      "ignoreWasSetByUser" : 0,
      "ignore" : 1,
      "hidden" : 0,
      "outputPathIsSetByUser" : 0,
      "inputAbbreviatedPath" : "\/sass\/_2x.scss",
      "outputStyle" : 3,
      "shouldRunBless" : 0,
      "outputAbbreviatedPath" : "\/css\/_2x.css",
      "fileType" : 4,
      "debugStyle" : 0
    },
    "\/images\/give.png" : {
      "ignoreWasSetByUser" : 0,
      "ignore" : 0,
      "hidden" : 0,
      "outputPathIsSetByUser" : 0,
      "inputAbbreviatedPath" : "\/images\/give.png",
      "processed" : 0,
      "outputAbbreviatedPath" : "\/images\/give.png",
      "initialSize" : 769,
      "fileType" : 8192
    },
    "\/images\/advocate@2x.png" : {
      "ignoreWasSetByUser" : 0,
      "ignore" : 0,
      "hidden" : 0,
      "outputPathIsSetByUser" : 0,
      "inputAbbreviatedPath" : "\/images\/advocate@2x.png",
      "processed" : 0,
      "outputAbbreviatedPath" : "\/images\/advocate@2x.png",
      "initialSize" : 581,
      "fileType" : 8192
    },
    "\/scss\/_normalize.scss" : {
      "ignoreWasSetByUser" : 0,
      "ignore" : 1,
      "hidden" : 0,
      "outputPathIsSetByUser" : 0,
      "inputAbbreviatedPath" : "\/scss\/_normalize.scss",
      "outputStyle" : 3,
      "shouldRunBless" : 0,
      "outputAbbreviatedPath" : "\/css\/_normalize.css",
      "fileType" : 4,
      "debugStyle" : 0
    },
    "\/less\/login.less" : {
      "ignoreWasSetByUser" : 0,
      "ignore" : 0,
      "hidden" : 0,
      "outputPathIsSetByUser" : 0,
      "inputAbbreviatedPath" : "\/less\/login.less",
      "outputStyle" : 0,
      "shouldRunBless" : 0,
      "outputAbbreviatedPath" : "\/css\/login.css",
      "strictImports" : 0,
      "fileType" : 1,
      "debugStyle" : 0
    },
    "\/images\/custom-post-icon.png" : {
      "ignoreWasSetByUser" : 0,
      "ignore" : 0,
      "hidden" : 0,
      "outputPathIsSetByUser" : 0,
      "inputAbbreviatedPath" : "\/images\/custom-post-icon.png",
      "processed" : 0,
      "outputAbbreviatedPath" : "\/images\/custom-post-icon.png",
      "initialSize" : 462,
      "fileType" : 8192
    },
    "\/fonts\/tradegothic-boldcondtwenty-demo.html" : {
      "ignoreWasSetByUser" : 0,
      "ignore" : 0,
      "hidden" : 0,
      "outputPathIsSetByUser" : 0,
      "inputAbbreviatedPath" : "\/fonts\/tradegothic-boldcondtwenty-demo.html",
      "outputAbbreviatedPath" : "No Output Path",
      "fileType" : 2048
    },
    "\/images\/advocate.png" : {
      "ignoreWasSetByUser" : 0,
      "ignore" : 0,
      "hidden" : 0,
      "outputPathIsSetByUser" : 0,
      "inputAbbreviatedPath" : "\/images\/advocate.png",
      "processed" : 0,
      "outputAbbreviatedPath" : "\/images\/advocate.png",
      "initialSize" : 386,
      "fileType" : 8192
    },
    "\/images\/facebook_circle.png" : {
      "ignoreWasSetByUser" : 0,
      "ignore" : 0,
      "hidden" : 0,
      "outputPathIsSetByUser" : 0,
      "inputAbbreviatedPath" : "\/images\/facebook_circle.png",
      "processed" : 0,
      "outputAbbreviatedPath" : "\/images\/facebook_circle.png",
      "initialSize" : 927,
      "fileType" : 8192
    },
    "\/js\/libs\/modernizr.custom.min-ck.js" : {
      "ignoreWasSetByUser" : 0,
      "ignore" : 1,
      "hidden" : 0,
      "outputPathIsSetByUser" : 0,
      "inputAbbreviatedPath" : "\/js\/libs\/modernizr.custom.min-ck.js",
      "outputStyle" : 1,
      "syntaxCheckerStyle" : 1,
      "outputAbbreviatedPath" : "\/js\/libs\/modernizr.custom.min-ck-ck.js",
      "fileType" : 64
    },
    "\/fonts\/stylesheet.css" : {
      "ignoreWasSetByUser" : 0,
      "ignore" : 0,
      "hidden" : 0,
      "outputPathIsSetByUser" : 0,
      "inputAbbreviatedPath" : "\/fonts\/stylesheet.css",
      "outputAbbreviatedPath" : "No Output Path",
      "fileType" : 16
    },
    "\/css\/style.css" : {
      "ignoreWasSetByUser" : 0,
      "ignore" : 1,
      "hidden" : 0,
      "outputPathIsSetByUser" : 0,
      "inputAbbreviatedPath" : "\/css\/style.css",
      "outputAbbreviatedPath" : "No Output Path",
      "fileType" : 16
    },
    "\/images\/logo-mobile2.png" : {
      "ignoreWasSetByUser" : 0,
      "ignore" : 0,
      "hidden" : 0,
      "outputPathIsSetByUser" : 0,
      "inputAbbreviatedPath" : "\/images\/logo-mobile2.png",
      "processed" : 0,
      "outputAbbreviatedPath" : "\/images\/logo-mobile2.png",
      "initialSize" : 6791,
      "fileType" : 8192
    },
    "\/bones.php" : {
      "ignoreWasSetByUser" : 0,
      "ignore" : 0,
      "hidden" : 0,
      "outputPathIsSetByUser" : 0,
      "inputAbbreviatedPath" : "\/bones.php",
      "outputAbbreviatedPath" : "No Output Path",
      "fileType" : 2048
    },
    "\/images\/twitter_circle@2x.png" : {
      "ignoreWasSetByUser" : 0,
      "ignore" : 0,
      "hidden" : 0,
      "outputPathIsSetByUser" : 0,
      "inputAbbreviatedPath" : "\/images\/twitter_circle@2x.png",
      "processed" : 0,
      "outputAbbreviatedPath" : "\/images\/twitter_circle@2x.png",
      "initialSize" : 1882,
      "fileType" : 8192
    },
    "\/scss\/_buttons.scss" : {
      "ignoreWasSetByUser" : 0,
      "ignore" : 1,
      "hidden" : 0,
      "outputPathIsSetByUser" : 0,
      "inputAbbreviatedPath" : "\/scss\/_buttons.scss",
      "outputStyle" : 3,
      "shouldRunBless" : 0,
      "outputAbbreviatedPath" : "\/css\/_buttons.css",
      "fileType" : 4,
      "debugStyle" : 0
    },
    "\/sass\/_print.scss" : {
      "ignoreWasSetByUser" : 0,
      "ignore" : 1,
      "hidden" : 0,
      "outputPathIsSetByUser" : 0,
      "inputAbbreviatedPath" : "\/sass\/_print.scss",
      "outputStyle" : 3,
      "shouldRunBless" : 0,
      "outputAbbreviatedPath" : "\/css\/_print.css",
      "fileType" : 4,
      "debugStyle" : 0
    },
    "\/images\/menu-icon-large.png" : {
      "ignoreWasSetByUser" : 0,
      "ignore" : 0,
      "hidden" : 0,
      "outputPathIsSetByUser" : 0,
      "inputAbbreviatedPath" : "\/images\/menu-icon-large.png",
      "processed" : 0,
      "outputAbbreviatedPath" : "\/images\/menu-icon-large.png",
      "initialSize" : 1188,
      "fileType" : 8192
    },
    "\/images\/uwmc-avatar.png" : {
      "ignoreWasSetByUser" : 0,
      "ignore" : 0,
      "hidden" : 0,
      "outputPathIsSetByUser" : 0,
      "inputAbbreviatedPath" : "\/images\/uwmc-avatar.png",
      "processed" : 0,
      "outputAbbreviatedPath" : "\/images\/uwmc-avatar.png",
      "initialSize" : 3935,
      "fileType" : 8192
    },
    "\/images\/glyphicons-halflings-white.png" : {
      "ignoreWasSetByUser" : 0,
      "ignore" : 0,
      "hidden" : 0,
      "outputPathIsSetByUser" : 0,
      "inputAbbreviatedPath" : "\/images\/glyphicons-halflings-white.png",
      "processed" : 0,
      "outputAbbreviatedPath" : "\/images\/glyphicons-halflings-white.png",
      "initialSize" : 8777,
      "fileType" : 8192
    },
    "\/images\/rss_circle@2x.png" : {
      "ignoreWasSetByUser" : 0,
      "ignore" : 0,
      "hidden" : 0,
      "outputPathIsSetByUser" : 0,
      "inputAbbreviatedPath" : "\/images\/rss_circle@2x.png",
      "processed" : 0,
      "outputAbbreviatedPath" : "\/images\/rss_circle@2x.png",
      "initialSize" : 2432,
      "fileType" : 8192
    },
    "\/sass\/_768up.scss" : {
      "ignoreWasSetByUser" : 0,
      "ignore" : 1,
      "hidden" : 0,
      "outputPathIsSetByUser" : 0,
      "inputAbbreviatedPath" : "\/sass\/_768up.scss",
      "outputStyle" : 3,
      "shouldRunBless" : 0,
      "outputAbbreviatedPath" : "\/css\/_768up.css",
      "fileType" : 4,
      "debugStyle" : 0
    },
    "\/less\/_481up.less" : {
      "ignoreWasSetByUser" : 0,
      "ignore" : 1,
      "hidden" : 0,
      "outputPathIsSetByUser" : 0,
      "inputAbbreviatedPath" : "\/less\/_481up.less",
      "outputStyle" : 0,
      "shouldRunBless" : 0,
      "outputAbbreviatedPath" : "\/css\/_481up.css",
      "strictImports" : 0,
      "fileType" : 1,
      "debugStyle" : 0
    },
    "\/images\/logo.png" : {
      "ignoreWasSetByUser" : 0,
      "ignore" : 0,
      "hidden" : 0,
      "outputPathIsSetByUser" : 0,
      "inputAbbreviatedPath" : "\/images\/logo.png",
      "processed" : 0,
      "outputAbbreviatedPath" : "\/images\/logo.png",
      "initialSize" : 12581,
      "fileType" : 8192
    },
    "\/scss\/css\/buttons_full.css" : {
      "ignoreWasSetByUser" : 0,
      "ignore" : 1,
      "hidden" : 0,
      "outputPathIsSetByUser" : 0,
      "inputAbbreviatedPath" : "\/scss\/css\/buttons_full.css",
      "outputAbbreviatedPath" : "No Output Path",
      "fileType" : 16
    },
    "\/sass\/_1240up.scss" : {
      "ignoreWasSetByUser" : 0,
      "ignore" : 1,
      "hidden" : 0,
      "outputPathIsSetByUser" : 0,
      "inputAbbreviatedPath" : "\/sass\/_1240up.scss",
      "outputStyle" : 3,
      "shouldRunBless" : 0,
      "outputAbbreviatedPath" : "\/css\/_1240up.css",
      "fileType" : 4,
      "debugStyle" : 0
    },
    "\/css\/ie.css" : {
      "ignoreWasSetByUser" : 0,
      "ignore" : 1,
      "hidden" : 0,
      "outputPathIsSetByUser" : 0,
      "inputAbbreviatedPath" : "\/css\/ie.css",
      "outputAbbreviatedPath" : "No Output Path",
      "fileType" : 16
    },
    "\/images\/advocate2@2x.png" : {
      "ignoreWasSetByUser" : 0,
      "ignore" : 0,
      "hidden" : 0,
      "outputPathIsSetByUser" : 0,
      "inputAbbreviatedPath" : "\/images\/advocate2@2x.png",
      "processed" : 0,
      "outputAbbreviatedPath" : "\/images\/advocate2@2x.png",
      "initialSize" : 869,
      "fileType" : 8192
    },
    "\/scss\/not_used\/_buttons_old.scss" : {
      "ignoreWasSetByUser" : 0,
      "ignore" : 1,
      "hidden" : 0,
      "outputPathIsSetByUser" : 0,
      "inputAbbreviatedPath" : "\/scss\/not_used\/_buttons_old.scss",
      "outputStyle" : 3,
      "shouldRunBless" : 0,
      "outputAbbreviatedPath" : "\/scss\/css\/_buttons_old.css",
      "fileType" : 4,
      "debugStyle" : 0
    },
    "\/images\/give@2x.png" : {
      "ignoreWasSetByUser" : 0,
      "ignore" : 0,
      "hidden" : 0,
      "outputPathIsSetByUser" : 0,
      "inputAbbreviatedPath" : "\/images\/give@2x.png",
      "processed" : 0,
      "outputAbbreviatedPath" : "\/images\/give@2x.png",
      "initialSize" : 1389,
      "fileType" : 8192
    },
    "\/css\/not_used\/occ_buttons.css" : {
      "ignoreWasSetByUser" : 0,
      "ignore" : 0,
      "hidden" : 0,
      "outputPathIsSetByUser" : 0,
      "inputAbbreviatedPath" : "\/css\/not_used\/occ_buttons.css",
      "outputAbbreviatedPath" : "No Output Path",
      "fileType" : 16
    },
    "\/images\/volunteer@2x.png" : {
      "ignoreWasSetByUser" : 0,
      "ignore" : 0,
      "hidden" : 0,
      "outputPathIsSetByUser" : 0,
      "inputAbbreviatedPath" : "\/images\/volunteer@2x.png",
      "processed" : 0,
      "outputAbbreviatedPath" : "\/images\/volunteer@2x.png",
      "initialSize" : 1330,
      "fileType" : 8192
    },
    "\/css\/print.css" : {
      "ignoreWasSetByUser" : 0,
      "ignore" : 0,
      "hidden" : 0,
      "outputPathIsSetByUser" : 0,
      "inputAbbreviatedPath" : "\/css\/print.css",
      "outputAbbreviatedPath" : "No Output Path",
      "fileType" : 16
    },
    "\/less\/ie.less" : {
      "ignoreWasSetByUser" : 0,
      "ignore" : 0,
      "hidden" : 0,
      "outputPathIsSetByUser" : 0,
      "inputAbbreviatedPath" : "\/less\/ie.less",
      "outputStyle" : 0,
      "shouldRunBless" : 0,
      "outputAbbreviatedPath" : "\/css\/ie.css",
      "strictImports" : 0,
      "fileType" : 1,
      "debugStyle" : 0
    },
    "\/js\/uwmctweets-ck.js" : {
      "ignoreWasSetByUser" : 0,
      "ignore" : 1,
      "hidden" : 0,
      "outputPathIsSetByUser" : 0,
      "inputAbbreviatedPath" : "\/js\/uwmctweets-ck.js",
      "outputStyle" : 1,
      "syntaxCheckerStyle" : 1,
      "outputAbbreviatedPath" : "\/js\/uwmctweets-ck-ck.js",
      "fileType" : 64
    },
    "\/js\/awesomechart.js" : {
      "ignoreWasSetByUser" : 0,
      "ignore" : 0,
      "hidden" : 0,
      "outputPathIsSetByUser" : 0,
      "inputAbbreviatedPath" : "\/js\/awesomechart.js",
      "outputStyle" : 1,
      "syntaxCheckerStyle" : 1,
      "outputAbbreviatedPath" : "\/js\/awesomechart-ck.js",
      "fileType" : 64
    },
    "\/scss\/_print.scss" : {
      "ignoreWasSetByUser" : 0,
      "ignore" : 1,
      "hidden" : 0,
      "outputPathIsSetByUser" : 0,
      "inputAbbreviatedPath" : "\/scss\/_print.scss",
      "outputStyle" : 3,
      "shouldRunBless" : 0,
      "outputAbbreviatedPath" : "\/css\/_print.css",
      "fileType" : 4,
      "debugStyle" : 0
    },
    "\/images\/advocate2.png" : {
      "ignoreWasSetByUser" : 0,
      "ignore" : 0,
      "hidden" : 0,
      "outputPathIsSetByUser" : 0,
      "inputAbbreviatedPath" : "\/images\/advocate2.png",
      "processed" : 0,
      "outputAbbreviatedPath" : "\/images\/advocate2.png",
      "initialSize" : 521,
      "fileType" : 8192
    },
    "\/admin.php" : {
      "ignoreWasSetByUser" : 0,
      "ignore" : 0,
      "hidden" : 0,
      "outputPathIsSetByUser" : 0,
      "inputAbbreviatedPath" : "\/admin.php",
      "outputAbbreviatedPath" : "No Output Path",
      "fileType" : 2048
    },
    "\/images\/twitter_circle.png" : {
      "ignoreWasSetByUser" : 0,
      "ignore" : 0,
      "hidden" : 0,
      "outputPathIsSetByUser" : 0,
      "inputAbbreviatedPath" : "\/images\/twitter_circle.png",
      "processed" : 0,
      "outputAbbreviatedPath" : "\/images\/twitter_circle.png",
      "initialSize" : 1126,
      "fileType" : 8192
    },
    "\/scss\/_common.scss" : {
      "ignoreWasSetByUser" : 0,
      "ignore" : 1,
      "hidden" : 0,
      "outputPathIsSetByUser" : 0,
      "inputAbbreviatedPath" : "\/scss\/_common.scss",
      "outputStyle" : 3,
      "shouldRunBless" : 0,
      "outputAbbreviatedPath" : "\/css\/_common.css",
      "fileType" : 4,
      "debugStyle" : 0
    },
    "\/images\/login-logo.png" : {
      "ignoreWasSetByUser" : 0,
      "ignore" : 0,
      "hidden" : 0,
      "outputPathIsSetByUser" : 0,
      "inputAbbreviatedPath" : "\/images\/login-logo.png",
      "processed" : 0,
      "outputAbbreviatedPath" : "\/images\/login-logo.png",
      "initialSize" : 7019,
      "fileType" : 8192
    },
    "\/translation\/translation.php" : {
      "ignoreWasSetByUser" : 0,
      "ignore" : 0,
      "hidden" : 0,
      "outputPathIsSetByUser" : 0,
      "inputAbbreviatedPath" : "\/translation\/translation.php",
      "outputAbbreviatedPath" : "No Output Path",
      "fileType" : 2048
    },
    "\/scss\/_768up.scss" : {
      "ignoreWasSetByUser" : 0,
      "ignore" : 1,
      "hidden" : 0,
      "outputPathIsSetByUser" : 0,
      "inputAbbreviatedPath" : "\/scss\/_768up.scss",
      "outputStyle" : 3,
      "shouldRunBless" : 0,
      "outputAbbreviatedPath" : "\/css\/_768up.css",
      "fileType" : 4,
      "debugStyle" : 0
    },
    "\/sass\/not_used\/occ_buttons.scss" : {
      "ignoreWasSetByUser" : 0,
      "ignore" : 0,
      "hidden" : 0,
      "outputPathIsSetByUser" : 0,
      "inputAbbreviatedPath" : "\/sass\/not_used\/occ_buttons.scss",
      "outputStyle" : 3,
      "shouldRunBless" : 0,
      "outputAbbreviatedPath" : "\/sass\/css\/occ_buttons.css",
      "fileType" : 4,
      "debugStyle" : 0
    },
    "\/js\/libs\/modernizr.custom.min.js" : {
      "ignoreWasSetByUser" : 0,
      "ignore" : 0,
      "hidden" : 0,
      "outputPathIsSetByUser" : 0,
      "inputAbbreviatedPath" : "\/js\/libs\/modernizr.custom.min.js",
      "outputStyle" : 1,
      "syntaxCheckerStyle" : 1,
      "outputAbbreviatedPath" : "\/js\/libs\/modernizr.custom.min-ck.js",
      "fileType" : 64
    },
    "\/images\/flickr_circle@2x.png" : {
      "ignoreWasSetByUser" : 0,
      "ignore" : 0,
      "hidden" : 0,
      "outputPathIsSetByUser" : 0,
      "inputAbbreviatedPath" : "\/images\/flickr_circle@2x.png",
      "processed" : 0,
      "outputAbbreviatedPath" : "\/images\/flickr_circle@2x.png",
      "initialSize" : 1746,
      "fileType" : 8192
    },
    "\/sass\/_grid.scss" : {
      "ignoreWasSetByUser" : 0,
      "ignore" : 1,
      "hidden" : 0,
      "outputPathIsSetByUser" : 0,
      "inputAbbreviatedPath" : "\/sass\/_grid.scss",
      "outputStyle" : 3,
      "shouldRunBless" : 0,
      "outputAbbreviatedPath" : "\/css\/_grid.css",
      "fileType" : 4,
      "debugStyle" : 0
    },
    "\/scss\/_mixins.scss" : {
      "ignoreWasSetByUser" : 0,
      "ignore" : 1,
      "hidden" : 0,
      "outputPathIsSetByUser" : 0,
      "inputAbbreviatedPath" : "\/scss\/_mixins.scss",
      "outputStyle" : 3,
      "shouldRunBless" : 0,
      "outputAbbreviatedPath" : "\/css\/_mixins.css",
      "fileType" : 4,
      "debugStyle" : 0
    },
    "\/js\/awesomechart-ck.js" : {
      "ignoreWasSetByUser" : 0,
      "ignore" : 1,
      "hidden" : 0,
      "outputPathIsSetByUser" : 0,
      "inputAbbreviatedPath" : "\/js\/awesomechart-ck.js",
      "outputStyle" : 1,
      "syntaxCheckerStyle" : 1,
      "outputAbbreviatedPath" : "\/js\/awesomechart-ck-ck.js",
      "fileType" : 64
    }
  },
  "manualImportLinks" : [

  ],
  "projectSettings" : {
    "hamlNoEscapeInAttributes" : 0,
    "kitAutoOutputPathStyle" : 0,
    "lessOutputStyle" : 0,
    "hamlAutoOutputPathReplace2" : "",
    "draggedImportConcatenationStyle" : 1,
    "jadeAutoOutputPathStyle" : 0,
    "hamlEscapeHTMLCharacters" : 0,
    "javascriptAutoOutputPathStyle" : 0,
    "hamlOutputFormat" : 2,
    "stylusAutoOutputPathReplace1" : "stylus",
    "lessStrictImports" : 0,
    "sassAutoOutputPathStyle" : 2,
    "stylusAutoOutputPathReplace2" : "css",
    "lessAutoOutputPathStyle" : 2,
    "genericWebpageFileExtensionsString" : "html, htm, shtml, shtm, xhtml, php, jsp, asp, aspx, erb, ctp",
    "coffeeMinifyOutput" : 1,
    "javascriptOutputSuffix" : "-ck",
    "jadeOutputStyle" : 0,
    "coffeeAutoOutputPathStyle" : 0,
    "autoSyncProjectSettingsFile" : 1,
    "lessAutoOutputPathReplace1" : "less",
    "jadeAutoOutputPathReplace1" : "",
    "lessAutoOutputPathRelativePath" : "..\/css",
    "hamlAutoOutputPathRelativePath" : "",
    "jsCheckerReservedNamesString" : "",
    "javascriptOutputStyle" : 1,
    "stylusDebugStyle" : 0,
    "hamlUseCDATA" : 0,
    "hamlAutoOutputPathStyle" : 0,
    "sassDebugStyle" : 0,
    "hamlOutputStyle" : 0,
    "stylusAutoOutputPathRelativePath" : "..\/css",
    "jsCheckerIndent" : 4,
    "kitAutoOutputPathRelativePath" : "",
    "lessAutoOutputPathReplace2" : "css",
    "jadeAutoOutputPathReplace2" : "",
    "shouldRunBless" : 0,
    "stylusAutoOutputPathStyle" : 2,
    "coffeeCheckOutputStyle" : 0,
    "slimOutputStyle" : 1,
    "javascriptSyntaxCheckerStyle" : 1,
    "sassAutoOutputPathReplace1" : "sass",
    "slimAutoOutputPathReplace1" : "",
    "sassOutputStyle" : 3,
    "coffeeAutoOutputPathRelativePath" : "",
    "slimCompileOnly" : 0,
    "slimLogicless" : 0,
    "uglifyIndent" : 4,
    "jadeAutoOutputPathRelativePath" : "",
    "hamlUseUnixNewlines" : 0,
    "hamlAutoOutputPathReplace1" : "",
    "javascriptAutoOutputPathReplace1" : "",
    "stylusOutputStyle" : 0,
    "javascriptAutoOutputPathReplace2" : "",
    "sassAutoOutputPathRelativePath" : "..\/css",
    "coffeeAutoOutputPathReplace1" : "",
    "hamlUseDoubleQuotes" : 0,
    "coffeeAutoOutputPathReplace2" : "",
    "kitAutoOutputPathReplace1" : "",
    "uglifyReservedNamesString" : "",
    "coffeeOutputStyle" : 0,
    "slimAutoOutputPathRelativePath" : "",
    "jsHintFlags" : {
      "latedef" : 1,
      "newcap" : 1,
      "curly" : 1,
      "trailing" : 1,
      "nonew" : 1,
      "withstmt" : 0,
      "yui" : 0,
      "mootools" : 0,
      "proto" : 0,
      "boss" : 0,
      "funcscope" : 0,
      "regexdash" : 0,
      "jquery" : 1,
      "esnext" : 0,
      "camelcase" : 0,
      "es5" : 0,
      "dojo" : 0,
      "strict" : 0,
      "devel" : 0,
      "onecase" : 0,
      "wsh" : 0,
      "nonstandard" : 0,
      "asi" : 0,
      "smarttabs" : 0,
      "rhino" : 0,
      "noempty" : 0,
      "lastsemic" : 0,
      "eqnull" : 0,
      "eqeqeq" : 1,
      "couch" : 0,
      "evil" : 0,
      "expr" : 0,
      "immed" : 0,
      "globalstrict" : 0,
      "undef" : 1,
      "iterator" : 0,
      "prototypejs" : 0,
      "noarg" : 1,
      "supernew" : 0,
      "node" : 0,
      "unused" : 1,
      "debug" : 0,
      "bitwise" : 1,
      "white" : 0,
      "browser" : 1,
      "worker" : 0,
      "laxcomma" : 0,
      "multistr" : 0,
      "shadow" : 0,
      "sub" : 0,
      "regexp" : 1,
      "scripturl" : 0,
      "forin" : 0,
      "loopfunc" : 0,
      "laxbreak" : 0,
      "plusplus" : 0
    },
    "jsLintFlags" : {
      "white" : 0,
      "bitwise" : 0,
      "regexp" : 0,
      "vars" : 0,
      "anon" : 0,
      "sub" : 0,
      "stupid" : 0,
      "nomen" : 0,
      "unparam" : 0,
      "newcap" : 0,
      "'continue'" : 0,
      "sloppy" : 0,
      "fragment" : 0,
      "undef" : 0,
      "es5" : 0,
      "browser" : 1,
      "properties" : 0,
      "forin" : 0,
      "plusplus" : 0,
      "debug" : 0,
      "eqeq" : 0,
      "confusion" : 0,
      "evil" : 0,
      "on" : 0,
      "windows" : 0,
      "devel" : 0,
      "rhino" : 0,
      "node" : 0,
      "css" : 0
    },
    "uglifyFlags" : {
      "no-mangle-functions" : 0,
      "no-mangle" : 0,
      "no-copyright" : 0,
      "no-dead-code" : 0,
      "inline-script" : 0,
      "ascii" : 0,
      "unsafe" : 0,
      "mangle-toplevel" : 0,
      "no-seqs" : 1,
      "beautify" : 1,
      "lift-vars" : 0,
      "consolidate-primitive-values" : 0,
      "no-squeeze" : 0
    },
    "sassAutoOutputPathReplace2" : "css",
    "slimAutoOutputPathReplace2" : "",
    "jadeCompileDebug" : 1,
    "slimRailsCompatible" : 0,
    "kitAutoOutputPathReplace2" : "",
    "lessDebugStyle" : 0,
    "javascriptAutoOutputPathRelativePath" : "",
    "slimAutoOutputPathStyle" : 0
  },
  "projectAttributes" : {
    "bourbonEnabled" : 1,
    "displayValue" : "library",
    "displayValueWasSetByUser" : 1,
    "compassEnabled" : 0
  }
}